esmvaltool_sample_data/__init__.py
esmvaltool_sample_data/data/timeseries/CMIP6/CMIP/AS-RCEC/TaiESM1/historical/r1i1p1f1/Amon/ta/gn/v20200623/ta_Amon_TaiESM1_historical_r1i1p1f1_gn_185001-201412.nc
esmvaltool_sample_data/data/timeseries/CMIP6/CMIP/AS-RCEC/TaiESM1/historical/r1i1p1f1/day/ta/gn/v20200626/ta_day_TaiESM1_historical_r1i1p1f1_gn_20000101-20091231.nc
esmvaltool_sample_data/data/timeseries/CMIP6/CMIP/AWI/AWI-CM-1-1-MR/historical/r1i1p1f1/Amon/ta/gn/v20181218/ta_Amon_AWI-CM-1-1-MR_historical_r1i1p1f1_gn_195001-195012.nc
esmvaltool_sample_data/data/timeseries/CMIP6/CMIP/AWI/AWI-CM-1-1-MR/historical/r1i1p1f1/Amon/ta/gn/v20181218/ta_Amon_AWI-CM-1-1-MR_historical_r1i1p1f1_gn_195101-195112.nc
esmvaltool_sample_data/data/timeseries/CMIP6/CMIP/AWI/AWI-CM-1-1-MR/historical/r1i1p1f1/Amon/ta/gn/v20181218/ta_Amon_AWI-CM-1-1-MR_historical_r1i1p1f1_gn_195201-195212.nc
esmvaltool_sample_data/data/timeseries/CMIP6/CMIP/AWI/AWI-CM-1-1-MR/historical/r1i1p1f1/Amon/ta/gn/v20181218/ta_Amon_AWI-CM-1-1-MR_historical_r1i1p1f1_gn_195301-195312.nc
esmvaltool_sample_data/data/timeseries/CMIP6/CMIP/AWI/AWI-CM-1-1-MR/historical/r1i1p1f1/Amon/ta/gn/v20181218/ta_Amon_AWI-CM-1-1-MR_historical_r1i1p1f1_gn_195401-195412.nc
esmvaltool_sample_data/data/timeseries/CMIP6/CMIP/AWI/AWI-CM-1-1-MR/historical/r1i1p1f1/Amon/ta/gn/v20181218/ta_Amon_AWI-CM-1-1-MR_historical_r1i1p1f1_gn_195501-195512.nc
esmvaltool_sample_data/data/timeseries/CMIP6/CMIP/AWI/AWI-CM-1-1-MR/historical/r1i1p1f1/Amon/ta/gn/v20181218/ta_Amon_AWI-CM-1-1-MR_historical_r1i1p1f1_gn_195601-195612.nc
esmvaltool_sample_data/data/timeseries/CMIP6/CMIP/AWI/AWI-CM-1-1-MR/historical/r1i1p1f1/Amon/ta/gn/v20181218/ta_Amon_AWI-CM-1-1-MR_historical_r1i1p1f1_gn_195701-195712.nc
esmvaltool_sample_data/data/timeseries/CMIP6/CMIP/AWI/AWI-CM-1-1-MR/historical/r1i1p1f1/Amon/ta/gn/v20181218/ta_Amon_AWI-CM-1-1-MR_historical_r1i1p1f1_gn_195801-195812.nc
esmvaltool_sample_data-0.0.4.dist-info/licenses/LICENSE
esmvaltool_sample_data-0.0.4.dist-info/METADATA
esmvaltool_sample_data-0.0.4.dist-info/WHEEL
esmvaltool_sample_data-0.0.4.dist-info/top_level.txt
esmvaltool_sample_data-0.0.4.dist-info/RECORD
