Metadata-Version: 2.4
Name: ESMValTool_sample_data
Version: 0.0.4
Summary: ESMValTool sample data
Home-page: https://github.com/ESMValGroup/ESMValTool_sample_data
Author: Stef Smeets, Bouwe Andela
License: Apache 2.0; CC BY-SA 4.0
Keywords: ESMValTool
Classifier: Development Status :: 2 - Pre-Alpha
Classifier: Intended Audience :: Developers
Classifier: Intended Audience :: Science/Research
Classifier: License :: OSI Approved :: Apache Software License
Classifier: License :: Other/Proprietary License
Classifier: Natural Language :: English
Classifier: Programming Language :: Python :: 3
Classifier: Programming Language :: Python :: 3.9
Classifier: Programming Language :: Python :: 3.10
Classifier: Programming Language :: Python :: 3.11
Classifier: Programming Language :: Python :: 3.12
Classifier: Programming Language :: Python :: 3.13
Classifier: Topic :: Scientific/Engineering
Classifier: Topic :: Scientific/Engineering :: Atmospheric Science
Classifier: Topic :: Scientific/Engineering :: GIS
Classifier: Topic :: Scientific/Engineering :: Hydrology
Classifier: Topic :: Scientific/Engineering :: Physics
License-File: LICENSE
Requires-Dist: scitools-iris>=3.6
Provides-Extra: develop
Requires-Dist: codespell; extra == "develop"
Requires-Dist: docformatter; extra == "develop"
Requires-Dist: esgf-pyclient; extra == "develop"
Requires-Dist: isort; extra == "develop"
Requires-Dist: myproxyclient; extra == "develop"
Requires-Dist: pre-commit; extra == "develop"
Requires-Dist: prospector[with_pyroma]!=1.1.6.3,!=1.1.6.4; extra == "develop"
Requires-Dist: pytest; extra == "develop"
Requires-Dist: yamllint; extra == "develop"
Requires-Dist: yapf; extra == "develop"
Dynamic: author
Dynamic: classifier
Dynamic: description
Dynamic: description-content-type
Dynamic: home-page
Dynamic: keywords
Dynamic: license
Dynamic: license-file
Dynamic: provides-extra
Dynamic: requires-dist
Dynamic: summary
